alfasim_score/__init__.py
alfasim_score/common.py
alfasim_score/conftest.py
alfasim_score/constants.py
alfasim_score/units.py
alfasim_score/_tests/test_smoke.py
alfasim_score/converter/__init__.py
alfasim_score/converter/alfacase/alfasim_score_converter.py
alfasim_score/converter/alfacase/apb_plugin_data.py
alfasim_score/converter/alfacase/base_operation.py
alfasim_score/converter/alfacase/convert_alfacase.py
alfasim_score/converter/alfacase/convert_plugin_data.py
alfasim_score/converter/alfacase/injection_operation.py
alfasim_score/converter/alfacase/production_operation.py
alfasim_score/converter/alfacase/score_input_data.py
alfasim_score/converter/alfacase/score_input_reader.py
alfasim_score/converter/alfacase/score_output_generator.py
alfasim_score/converter/alfacase/_tests/test_build_injection_alfacase.py
alfasim_score/converter/alfacase/_tests/test_build_production_alfacase.py
alfasim_score/converter/alfacase/_tests/test_convert_alfacase.py
alfasim_score/converter/alfacase/_tests/test_convert_base_alfacase.py
alfasim_score/converter/alfacase/_tests/test_convert_casing.py
alfasim_score/converter/alfacase/_tests/test_convert_formation.py
alfasim_score/converter/alfacase/_tests/test_convert_materials.py
alfasim_score/converter/alfacase/_tests/test_convert_nodes.py
alfasim_score/converter/alfacase/_tests/test_convert_well_environment.py
alfasim_score/converter/alfacase/_tests/test_convert_well_trajectory.py
alfasim_score/converter/alfacase/_tests/test_output_reader.py
alfasim_score/converter/alfacase/_tests/test_output_results.py
alfasim_score/converter/alfacase/_tests/test_score_input_data.py
alfasim_score/converter/alfacase/_tests/data/score_input_gas_lift.json
alfasim_score/converter/alfacase/_tests/data/score_input_injection_operation.json
alfasim_score/converter/alfacase/_tests/data/score_input_natural_flow.json
alfasim_score/converter/alfacase/_tests/data/score_output_example.json
alfasim_score/converter/alfacase/_tests/data/case.data/results/results_00000
alfasim_score-1.0.0.dist-info/licenses/LICENSE
alfasim_score-1.0.0.dist-info/METADATA
alfasim_score-1.0.0.dist-info/WHEEL
alfasim_score-1.0.0.dist-info/top_level.txt
alfasim_score-1.0.0.dist-info/RECORD
