Metadata-Version: 2.4
Name: alfasim-score
Version: 1.0.0
Summary: Python package to convert the SCORE input JSON to Alfacase
Home-page: https://github.com/ESSS/alfasim-score
Author: ESSS
Author-email: foss@esss.co
License: MIT license
Keywords: ALFAsim,Score
Classifier: Development Status :: 5 - Production/Stable
Classifier: Intended Audience :: Developers
Classifier: License :: OSI Approved :: MIT License
Classifier: Programming Language :: Python :: 3.8
Classifier: Programming Language :: Python :: 3.9
Classifier: Programming Language :: Python :: 3.10
Classifier: Programming Language :: Python :: 3.11
Classifier: Programming Language :: Python :: 3.12
Requires-Python: >=3.8
License-File: LICENSE
Requires-Dist: alfasim-sdk==1.0.0
Requires-Dist: attrs>=18.1.0
Requires-Dist: numpy>=1.11.0
Requires-Dist: pandas>=2.0.0
Requires-Dist: oop-ext>=1.1
Requires-Dist: typing_extensions
Provides-Extra: testing
Requires-Dist: codecov; extra == "testing"
Requires-Dist: mypy; extra == "testing"
Requires-Dist: pre-commit; extra == "testing"
Requires-Dist: pytest; extra == "testing"
Requires-Dist: pytest-cov; extra == "testing"
Requires-Dist: pytest-mock; extra == "testing"
Requires-Dist: pytest-regressions; extra == "testing"
Requires-Dist: tox; extra == "testing"
Dynamic: author
Dynamic: author-email
Dynamic: classifier
Dynamic: description
Dynamic: home-page
Dynamic: keywords
Dynamic: license
Dynamic: license-file
Dynamic: provides-extra
Dynamic: requires-dist
Dynamic: requires-python
Dynamic: summary
